cxflow/__init__.py
cxflow/constants.py
cxflow/entry_point.py
cxflow/main_loop.py
cxflow/types.py
cxflow/cli/__init__.py
cxflow/cli/args.py
cxflow/cli/common.py
cxflow/cli/dataset.py
cxflow/cli/eval.py
cxflow/cli/grid_search.py
cxflow/cli/ls.py
cxflow/cli/prune.py
cxflow/cli/resume.py
cxflow/cli/train.py
cxflow/cli/util.py
cxflow/datasets/__init__.py
cxflow/datasets/abstract_dataset.py
cxflow/datasets/base_dataset.py
cxflow/datasets/downloadable_dataset.py
cxflow/datasets/stream_wrapper.py
cxflow/hooks/__init__.py
cxflow/hooks/abstract_hook.py
cxflow/hooks/accumulate_variables.py
cxflow/hooks/check.py
cxflow/hooks/compute_stats.py
cxflow/hooks/every_n_epoch.py
cxflow/hooks/log_dir.py
cxflow/hooks/log_profile.py
cxflow/hooks/log_variables.py
cxflow/hooks/on_plateau.py
cxflow/hooks/save.py
cxflow/hooks/save_cm.py
cxflow/hooks/show_progress.py
cxflow/hooks/stop_after.py
cxflow/hooks/stop_on_nan.py
cxflow/hooks/stop_on_plateau.py
cxflow/hooks/write_csv.py
cxflow/models/__init__.py
cxflow/models/abstract_model.py
cxflow/models/ensemble.py
cxflow/models/sequence.py
cxflow/tests/__init__.py
cxflow/tests/main_loop_test.py
cxflow/tests/test_core.py
cxflow/utils/__init__.py
cxflow/utils/config.py
cxflow/utils/confusion_matrix.py
cxflow/utils/download.py
cxflow/utils/misc.py
cxflow/utils/names.py
cxflow/utils/profile.py
cxflow/utils/reflection.py
cxflow/utils/training_trace.py
cxflow/utils/yaml.py
cxflow-0.12.0.dist-info/METADATA
cxflow-0.12.0.dist-info/RECORD
cxflow-0.12.0.dist-info/WHEEL
cxflow-0.12.0.dist-info/entry_points.txt
cxflow-0.12.0.dist-info/top_level.txt
